analyze/__init__.py
analyze/clustering.py
analyze/cmip_handler.py
analyze/combine_variables.py
analyze/concise_dataframe.py
analyze/discontinuous_grid_patcher.py
analyze/find_matches.py
analyze/globals.py
analyze/inferred_variable_field.py
analyze/io.py
analyze/merge_candidate_regions.py
analyze/pre_process.py
analyze/region_calculation.py
analyze/region_finding.py
analyze/time_statistics.py
analyze/tipping_criteria.py
analyze/tools.py
analyze/xarray_tools.py
bin/oet_plot
optim_esm_tools/__init__.py
optim_esm_tools/_test_utils.py
optim_esm_tools/config.py
optim_esm_tools/optim_esm_conf.ini
optim_esm_tools/py.typed
optim_esm_tools/utils.py
optim_esm_tools/analyze/__init__.py
optim_esm_tools/analyze/clustering.py
optim_esm_tools/analyze/cmip_handler.py
optim_esm_tools/analyze/combine_variables.py
optim_esm_tools/analyze/concise_dataframe.py
optim_esm_tools/analyze/discontinuous_grid_patcher.py
optim_esm_tools/analyze/find_matches.py
optim_esm_tools/analyze/globals.py
optim_esm_tools/analyze/inferred_variable_field.py
optim_esm_tools/analyze/io.py
optim_esm_tools/analyze/merge_candidate_regions.py
optim_esm_tools/analyze/pre_process.py
optim_esm_tools/analyze/region_calculation.py
optim_esm_tools/analyze/region_finding.py
optim_esm_tools/analyze/time_statistics.py
optim_esm_tools/analyze/tipping_criteria.py
optim_esm_tools/analyze/tools.py
optim_esm_tools/analyze/xarray_tools.py
optim_esm_tools/plotting/__init__.py
optim_esm_tools/plotting/map_maker.py
optim_esm_tools/plotting/plot.py
optim_esm_tools/plotting/plot_utils.py
optim_esm_tools/region_finding/__init__.py
optim_esm_tools/region_finding/_base.py
optim_esm_tools/region_finding/iter_ranges.py
optim_esm_tools/region_finding/keep_all.py
optim_esm_tools/region_finding/local_history.py
optim_esm_tools/region_finding/max_region.py
optim_esm_tools/region_finding/named_region.py
optim_esm_tools/region_finding/percentiles.py
optim_esm_tools/region_finding/product_percentiles.py
optim_esm_tools-5.0.0.dist-info/METADATA
optim_esm_tools-5.0.0.dist-info/WHEEL
optim_esm_tools-5.0.0.dist-info/top_level.txt
optim_esm_tools-5.0.0.dist-info/RECORD
