Metadata-Version: 2.1
Name: optim_esm_tools
Version: 5.0.0
Summary: Tools for OptimESM
Author: Joran R. Angevaare
Maintainer: Joran R. Angevaare
License: MIT
Project-URL: homepage, https://github.com/JoranAngevaare/optim_esm_tools
Project-URL: documentation, https://github.com/JoranAngevaare/optim_esm_tools/blob/master/notebooks/example.ipynb
Project-URL: repository, https://github.com/JoranAngevaare/optim_esm_tools
Classifier: Intended Audience :: Science/Research
Classifier: Development Status :: 4 - Beta
Classifier: Natural Language :: English
Classifier: Programming Language :: Python :: 3.8
Classifier: Programming Language :: Python :: 3.9
Classifier: Programming Language :: Python :: 3.10
Classifier: Programming Language :: Python :: 3.11
Classifier: Intended Audience :: Science/Research
Classifier: Programming Language :: Python :: Implementation :: CPython
Requires-Python: >=3.8
Requires-Dist: immutabledict
Requires-Dist: intake-esm
Requires-Dist: matplotlib
Requires-Dist: numba
Requires-Dist: numpy <2
Requires-Dist: pandas
Requires-Dist: tqdm
Requires-Dist: scipy
Requires-Dist: xarray <=2023.8.0
Requires-Dist: statsmodels
Requires-Dist: fiona <=1.9.6
Requires-Dist: shapely <2
Requires-Dist: geopandas <=0.13.2
Requires-Dist: rasterio <=1.4.3
Requires-Dist: regionmask
Requires-Dist: cartopy
Requires-Dist: nc-time-axis
Requires-Dist: cdo
Provides-Extra: test
Requires-Dist: coverage ; extra == 'test'
Requires-Dist: coveralls ; extra == 'test'
Requires-Dist: ipython ; extra == 'test'
Requires-Dist: matplotlib ; extra == 'test'
Requires-Dist: nbmake ; extra == 'test'
Requires-Dist: pytest ; extra == 'test'
Requires-Dist: tqdm ; extra == 'test'
